blacksheepsqlalchemy/__init__.py
blacksheep_sqlalchemy-0.0.4.dist-info/METADATA
blacksheep_sqlalchemy-0.0.4.dist-info/WHEEL
blacksheep_sqlalchemy-0.0.4.dist-info/licenses/LICENSE
blacksheep_sqlalchemy-0.0.4.dist-info/RECORD
