Metadata-Version: 2.4
Name: blacksheep-sqlalchemy
Version: 0.0.4
Summary: Extension for BlackSheep to use SQLAlchemy.
Project-URL: Homepage, https://github.com/Neoteroi/BlackSheep-SQLAlchemy
Project-URL: Bug Tracker, https://github.com/Neoteroi/BlackSheep-SQLAlchemy/issues
Author-email: Roberto Prevato <roberto.prevato@gmail.com>
License: MIT License
License-File: LICENSE
Keywords: blacksheep,database,orm,sqlalchemy
Classifier: Development Status :: 5 - Production/Stable
Classifier: Operating System :: OS Independent
Classifier: Programming Language :: Python :: 3
Classifier: Programming Language :: Python :: 3.8
Classifier: Programming Language :: Python :: 3.9
Classifier: Programming Language :: Python :: 3.10
Classifier: Programming Language :: Python :: 3.11
Classifier: Programming Language :: Python :: 3.12
Classifier: Programming Language :: Python :: 3.13
Requires-Python: >=3.7
Requires-Dist: blacksheep
Requires-Dist: sqlalchemy~=2.0.24
